modules/andm.v
module andm(input a, b, output out);
	assign out = a & b;
endmodule

modules/alu.v
module alu(input [63:0] in_A, in_B, input [2:0] control, output [63:0] out, 
	output zero);

	assign zero = (in_A == in_B) ? 1 : 0;

	always @(*) begin
		case (control)
			// addition
			3'b000: out = in_A + in_B;
			// subtraction
			3'b001: out = in_A - in_B;
			// and
			3'b010: out = in_A & in_B;
			// or
			3'b011: out = in_A | in_B;
			// shift left
			3'b100: out = in_A <<< 1;
			// shift right
			3'b101: out = in_A >>> 1;
			default: out = in_A + in_B;
		endcase
	end
endmodule

modules/control.v
module control(input [5:0] op, output reg [2:0] ALUCtrl, output reg branch, 
	writeEn, branchSwap);
	always @(op) begin
		// branch equal
		case (op)
			6'd10: begin
				ALUCtrl = 3'd0;
				branch = 1'b1;
				writeEn = 1'b0;
				branchSwap = 1'b1;
			end
			6'd0: begin
				ALUCtrl = 3'd0;
				branch = 1'b0;
				writeEn = 1'b1;
				branchSwap = 1'b0;
			end
			6'd1: begin
				ALUCtrl = 3'd1;
				branch = 1'b0;
				writeEn = 1'b1;
				branchSwap = 1'b0;
			end
			6'd2: begin
				ALUCtrl = 3'd2;
				branch = 1'b0;
				writeEn = 1'b1;
				branchSwap = 1'b0;
			end
			6'd3: begin
				ALUCtrl = 3'd3;
				branch = 1'b0;
				writeEn = 1'b1;
				branchSwap = 1'b0;
			end
			6'd4: begin
				ALUCtrl = 3'd4;
				branch = 1'b0;
				writeEn = 1'b1;
				branchSwap = 1'b0;
			end
			6'd5: begin
				ALUCtrl = 3'd5;
				branch = 1'b0;
				writeEn = 1'b1;
				branchSwap = 1'b0;
			end
			default: begin
				ALUCtrl = 3'd0;
				branch = 1'b0;
				writeEn = 1'b1;
				branchSwap = 1'b0;
			end
		endcase
	end
endmodule

modules/register_file.v
module register_file(input [5:0] readAdr1, readAdr2, writeAdr, 
	input [63:0] writeData, input writeEnable, clk, 
	output [63:0] readData1, readData2); 

	reg [63:0] register[64];

	assign readData1 = register[readAdr1];
	assign readData2 = register[readAdr2];

	always @(posedge clk) begin
		if (writeEnable)
			register[writeAdr] <= writeData;
	end

//-----------------------simulation-------------------------------//
	always @(*) begin
		$display("register_file: readAdr1:     %2d", readAdr1);
		$display("register_file: readAdr2:     %2d", readAdr2);
		$display("register_file: writeAdr:     %2d", writeAdr);
		$display("register_file: writeData:    %2d", writeData);
		$display("register_file: writeEnable:  %2d", writeEnable);
		$display("register_file: readData1:    %2d", readData1);
		$display("register_file: readData2:    %2d", readData2);
`ifndef SYNTHESIS
		for (int i = 0; i <= 3; i++) begin
			$display("register_file: register[%2d]: %2d", 
				i, register[i]);
		end
		$display();
`endif
	end

	initial begin
		$readmemb("data_register.txt", register, 0, 2);
	end

endmodule

modules/mux_6.v
module mux_6(input [5:0] a, b, input s, output reg [5:0] out);
	always @(s) begin
		if (s == 1'b1)
			out = b;
		else
			out = a;
	end
endmodule

modules/instruction_register.v
module instruction_register (input [63:0] in, input clk, output [63:0] out);
	reg [63:0] data;

	assign out = data;

	always @(posedge clk) begin
		data <= in;
	end

//------------------------simulation-------------------------------//
	always @(*) begin
		$display("instruction_register: data:    %2d", data);
		$display("instruction_register: in:  %2d", adr_in);
		$display("instruction_register: out: %2d\n", adr_out);
	end
endmodule

modules/ram.v
module ram(input [15:0] adr, input [63:0] writeData, input writeEn, clk, 
	output [63:0] readData);

	reg [63:0] mem[65536];
	assign readData = mem[adr];
	always @(posedge clk) begin
		if (writeEn) begin
			mem[adr] <= writeData;
		end
	end

//------------------------simulation-------------------------------//
	always @(*) begin
		$display("ram: adr:         %2d", adr);
		$display("ram: writeData:   %2d", writeData);
		$display("ram: writeEn:     %2d", writeEn);
		$display("ram: readData:    %2d", readData);
		$display("ram: mem_adr_op:  %2d", mem[adr][5:0]);
		$display("ram: mem_adr_rd:  %2d", mem[adr][11:6]);
		$display("ram: mem_adr_rs1: %2d", mem[adr][17:12]);
		$display("ram: mem_adr_rs2: %2d", mem[adr][23:18]);
		$display("ram: mem[%2d]:    %2d\n", adr, mem[adr]);
	end

	initial begin
		$readmemb("data_mem.txt", mem, 0, 5);
	end
endmodule

modules/adder.v
module adder(input [15:0] in_A, in_B, output [15:0] out);
	assign out = in_A + in_B;

//------------------------simulation-------------------------------//
	always @(*) begin
		$display("adder.v: in_A: : %2d", in_A);
		$display("adder.v: out: :  %2d\n", out);
	end
endmodule

modules/mux_16.v
module mux_16(input [15:0] a, b, input s, output reg [15:0] out);
	always @(s) begin
		if (s == 1'b1)
			out = b;
		else
			out = a;
	end
endmodule

modules/program_counter.v
module program_counter (input [15:0] in, input clk, output [15:0] out);
	reg [15:0] data;

	assign out = data;

	always @(posedge clk) begin
		data <= in;
	end

//------------------------simulation-------------------------------//
	always @(*) begin
		$display("program_counter: data:    %2d", data);
		$display("program_counter: in:  %2d", adr_in);
		$display("program_counter: out: %2d\n", adr_out);
	end
endmodule

modules/mips.v
/* verilator lint_off UNUSED */
/* verilator lint_off WIDTH */
module mips(input clk);
	wire [15:0] w1, w2, w3;
	wire [63:0] w4, w5, w6, w7, w12;
	wire [2:0] w8;
	wire [5:0] b1;
	wire w9, w10, w11, s1, s2;

	program_counter PC(.in(w1), .clk(clk), .out(w2));
	mux_16 MUX_16(.a(w2), .b(w5[33:18]), .s(w11), .out(w3));
	adder ADDER(.in_A(w3), .in_B(16'd1), .out(w1));
	ram MEM(.adr(w3), .writeData(64'd0), .writeEn(1'b0), .clk(1'b0), 
		.readData(w4));
	instruction_register INST_REG(.in(w4), .clk(clk), .out(w5));
	mux_6 MUX_6(.a(w5[23:18]), .b(w5[11:6]), .s(s1), .out(b1));
	register_file REG_FILE(.readAdr1(w5[17:12]), .readAdr2(b1), 
		.writeAdr(w5[11:6]), .writeData(w12), .writeEnable(s2), 
		.clk(clk), .readData1(w6), .readData2(w7));
	control CTRL(.op(w5[5:0]), .ALUCtrl(w8), .branch(w9), .writeEn(s2), 
		.branchSwap(s1));
	alu ALU(.in_A(w6), .in_B(w7), .control(w8), .out(w12), .zero(w10));
	andm ANDM(.a(w9), .b(w10), .out(w11));
endmodule
/* verilator lint_off UNUSED */
/* verilator lint_off WIDTH */

modules/mips.vcd
$version Generated by VerilatedVcd $end
$date Tue Feb 11 18:20:56 2020
 $end
$timescale   1ns $end

 $scope module TOP $end
  $var wire  1 < clk $end
  $scope module mips $end
   $var wire  6 . b1 [5:0] $end
   $var wire  1 < clk $end
   $var wire  1 2 s1 $end
   $var wire  1 3 s2 $end
   $var wire 16 # w1 [15:0] $end
   $var wire  1 0 w10 $end
   $var wire  1 1 w11 $end
   $var wire 64 + w12 [63:0] $end
   $var wire 16 4 w2 [15:0] $end
   $var wire 16 $ w3 [15:0] $end
   $var wire 64 % w4 [63:0] $end
   $var wire 64 5 w5 [63:0] $end
   $var wire 64 ' w6 [63:0] $end
   $var wire 64 ) w7 [63:0] $end
   $var wire  3 - w8 [2:0] $end
   $var wire  1 / w9 $end
   $scope module ADDER $end
    $var wire 16 $ in_A [15:0] $end
    $var wire 16 = in_B [15:0] $end
    $var wire 16 # out [15:0] $end
   $upscope $end
   $scope module ALU $end
    $var wire  3 - control [2:0] $end
    $var wire 64 ' in_A [63:0] $end
    $var wire 64 ) in_B [63:0] $end
    $var wire 64 + out [63:0] $end
    $var wire  1 0 zero $end
   $upscope $end
   $scope module ANDM $end
    $var wire  1 / a $end
    $var wire  1 0 b $end
    $var wire  1 1 out $end
   $upscope $end
   $scope module CTRL $end
    $var wire  3 - ALUCtrl [2:0] $end
    $var wire  1 / branch $end
    $var wire  1 2 branchSwap $end
    $var wire  6 ; op [5:0] $end
    $var wire  1 3 writeEn $end
   $upscope $end
   $scope module INST_REG $end
    $var wire  1 < clk $end
    $var wire 64 5 data [63:0] $end
    $var wire 64 % in [63:0] $end
    $var wire 64 5 out [63:0] $end
   $upscope $end
   $scope module MEM $end
    $var wire 16 $ adr [15:0] $end
    $var wire  1 @ clk $end
    $var wire 64 % readData [63:0] $end
    $var wire 64 > writeData [63:0] $end
    $var wire  1 @ writeEn $end
   $upscope $end
   $scope module MUX_16 $end
    $var wire 16 4 a [15:0] $end
    $var wire 16 7 b [15:0] $end
    $var wire 16 $ out [15:0] $end
    $var wire  1 1 s $end
   $upscope $end
   $scope module MUX_6 $end
    $var wire  6 8 a [5:0] $end
    $var wire  6 9 b [5:0] $end
    $var wire  6 . out [5:0] $end
    $var wire  1 2 s $end
   $upscope $end
   $scope module PC $end
    $var wire  1 < clk $end
    $var wire 16 4 data [15:0] $end
    $var wire 16 # in [15:0] $end
    $var wire 16 4 out [15:0] $end
   $upscope $end
   $scope module REG_FILE $end
    $var wire  1 < clk $end
    $var wire  6 : readAdr1 [5:0] $end
    $var wire  6 . readAdr2 [5:0] $end
    $var wire 64 ' readData1 [63:0] $end
    $var wire 64 ) readData2 [63:0] $end
    $var wire  6 9 writeAdr [5:0] $end
    $var wire 64 + writeData [63:0] $end
    $var wire  1 3 writeEnable $end
    $scope module unnamedblk1 $end
     $var wire 32 A i [31:0] $end
    $upscope $end
   $upscope $end
  $upscope $end
 $upscope $end
$enddefinitions $end


#1
b0000000000000001 #
b0000000000000000 $
b0000000000000000000000000000000000000000000010000001000011000000 %
b0000000000000000000000000000000000000000000000000000000000000000 '
b0000000000000000000000000000000000000000000000000000000000000000 )
b0000000000000000000000000000000000000000000000000000000000000000 +
b000 -
b000000 .
0/
10
01
02
13
b0000000000000000 4
b0000000000000000000000000000000000000000000000000000000000000000 5
b0000000000000000 7
b000000 8
b000000 9
b000000 :
b000000 ;
1<
b0000000000000001 =
b0000000000000000000000000000000000000000000000000000000000000000 >
0@
b00000000000000000000000000000100 A
#2
0<
#3
b0000000000000010 #
b0000000000000001 $
b0000000000000000000000000000000000000000000100000010000001001010 %
b0000000000000000000000000000000000000000000000000000000000000111 '
b0000000000000000000000000000000000000000000000000000000000000111 )
b0000000000000000000000000000000000000000000000000000000000001110 +
b000010 .
b0000000000000001 4
b0000000000000000000000000000000000000000000010000001000011000000 5
b0000000000000010 7
b000010 8
b000011 9
b000001 :
1<
#4
0<
#5
b0000000000000101 #
b0000000000000100 $
b0000000000000000000000000000000000000000000001000011000010000000 %
b000001 .
1/
11
12
03
b0000000000000010 4
b0000000000000000000000000000000000000000000100000010000001001010 5
b0000000000000100 7
b000100 8
b000001 9
b000010 :
b001010 ;
1<
#6
0<
#7
b0000000000000110 #
b0000000000000101 $
b0000000000000000000000000000000000000000000001000010000010000000 %
b0000000000000000000000000000000000000000000000000000000000001110 '
b0000000000000000000000000000000000000000000000000000000000010101 +
0/
00
01
02
13
b0000000000000101 4
b0000000000000000000000000000000000000000000001000011000010000000 5
b0000000000000001 7
b000001 8
b000010 9
b000011 :
b000000 ;
1<
#8
0<
#9
b0000000000000111 #
b0000000000000110 $
b0000000000000000000000000000000000000000000000000000000000000000 %
b0000000000000000000000000000000000000000000000000000000000010101 '
b0000000000000000000000000000000000000000000000000000000000011100 +
b0000000000000110 4
b0000000000000000000000000000000000000000000001000010000010000000 5
b000010 :
1<
#10
0<
#11
b0000000000001000 #
b0000000000000111 $
b0000000000000000000000000000000000000000000000000000000000000000 '
b0000000000000000000000000000000000000000000000000000000000000000 )
b0000000000000000000000000000000000000000000000000000000000000000 +
b000000 .
10
b0000000000000111 4
b0000000000000000000000000000000000000000000000000000000000000000 5
b0000000000000000 7
b000000 8
b000000 9
b000000 :
1<
#12
0<
#13
b0000000000001001 #
b0000000000001000 $
b0000000000001000 4
1<
#14
0<
#15
b0000000000001010 #
b0000000000001001 $
b0000000000001001 4
1<
#16
0<
#17
b0000000000001011 #
b0000000000001010 $
b0000000000001010 4
1<
#18
0<
#19
b0000000000001100 #
b0000000000001011 $
b0000000000001011 4
1<
