sr_latch.v
module sr_latch(input set, reset, enable, output out);
	assign out = (( out || ( set && enable)) && !( reset && enable));
endmodule

module test_sr_latch;
	reg [2:0] t_in;
	wire out;

	sr_latch M1(t_in[2], t_in[1], t_in[0], out);

	initial begin
		$dumpfile("test_sr_latch.vcd");
		$dumpvars(0,test_sr_latch);
		t_in = 3'b000;
		repeat(8) begin
			#1 t_in <= t_in + 3'b001;
		end
	end
endmodule

test_sr_latch.vcd
$date
	Thu Jul  4 03:08:38 2019
$end
$version
	GTKWave Analyzer v3.3.94 (w)1999-2018 BSI
$end
$timescale
	1 s
$end
$scope module test_sr_latch $end
$scope module M1 $end
$var wire 1 $ set $end
$var wire 1 # reset $end
$var wire 1 " enable $end
$var wire 1 % out $end
$upscope $end
$upscope $end
$enddefinitions $end
$dumpvars
#0
0"
0#
0$
x%
#1
1"
#2
0"
1#
#3
1"
0%
#4
0"
0#
1$
#5
1"
1%
#6
0"
1#
#7
0%
1"
#8
0"
0#
0$
1%
