modules/latch.v
module LATCH(input data, enable, preset, clear, output q, qbar);
	wire A, B, C, D, E;

	not(A, preset);
	not(B, clear);
	not(E, data);

	nand(C, data, enable);
	nand(D, E, enable);

	nand(q, C, A, qbar);
	nand(qbar, D, B, q);
endmodule

modules_tb/tb_latch.v
`include "latch.v"

module TB_LATCH;
	reg [3:0] t_in;
	wire q, qbar;

	LATCH T1(t_in[3], t_in[2], t_in[1], t_in[0], q, qbar);

	initial begin
		$dumpfile("dump_latch.vcd");
		$dumpvars(0);
		t_in = 4'b0000;
		repeat(16) begin
			#1 t_in <= t_in + 4'b0001;
		end
	end
endmodule

modules_tb/dump_latch.vcd
$date
	Tue Jul 30 06:33:07 2019
$end
$version
	Icarus Verilog
$end
$timescale
	1s
$end
$scope module TB_LATCH $end
$var wire 1 ! qbar $end
$var wire 1 " q $end
$var reg 4 # t_in [3:0] $end
$scope module T1 $end
$var wire 1 $ A $end
$var wire 1 % B $end
$var wire 1 & C $end
$var wire 1 ' D $end
$var wire 1 ( E $end
$var wire 1 ) clear $end
$var wire 1 * data $end
$var wire 1 + enable $end
$var wire 1 , preset $end
$var wire 1 " q $end
$var wire 1 ! qbar $end
$upscope $end
$upscope $end
$enddefinitions $end
#0
$dumpvars
0,
0+
0*
0)
1(
1'
1&
1%
1$
b0 #
x"
x!
$end
#1
0"
1!
0%
1)
b1 #
#2
0!
1"
0$
1%
1,
0)
b10 #
#3
1!
0%
1)
b11 #
#4
0"
0'
1$
1%
1+
0,
0)
b100 #
#5
0%
1)
b101 #
#6
1"
0$
1%
1,
0)
b110 #
#7
0%
1)
b111 #
#8
0!
0(
1'
1$
1%
1*
0+
0,
0)
b1000 #
#9
0"
1!
0%
1)
b1001 #
#10
0!
1"
0$
1%
1,
0)
b1010 #
#11
1!
0%
1)
b1011 #
#12
0!
0&
1$
1%
1+
0,
0)
b1100 #
#13
1!
0%
1)
b1101 #
#14
0!
0$
1%
1,
0)
b1110 #
#15
1!
0%
1)
b1111 #
#16
0!
1(
1&
1$
1%
0*
0+
0,
0)
b0 #
