sr_latch.v
module sr_latch(input set, reset, enable, output out);
	assign out = (( out || ( set && enable)) && !( reset && enable));
endmodule

module test_sr_latch;
	reg [2:0] t_in;
	wire out;

	sr_latch M1(t_in[2], t_in[1], t_in[0], out);

	initial begin
		$dumpfile("test_sr_latch.vcd");
		$dumpvars(0,test_sr_latch);
		t_in = 3'b000;
		repeat(8) begin
			#1 t_in <= t_in + 3'b001;
		end
	end
endmodule

d_latch.v
module d_latch(input data, enable, output out);
	sr_latch sr_latch1(data, !data, enable, out);
endmodule

module test_d_latch;
	reg [1:0] t_in;
	wire out;

	d_latch M1(t_in[1], t_in[0], out);

	initial begin
		$dumpfile("test_d_latch.vcd");
		$dumpvars(0,test_d_latch);
		t_in = 3'b000;
		repeat(8) begin
			#1 t_in <= t_in + 3'b001;
		end
	end
endmodule

modules_tb/tb_d_latch.v
`include "d_latch.v"

module tb_d_latch;
	reg [1:0] t_in;
	wire out;

	d_latch M1(t_in[1], t_in[0], out);

	initial begin
		$dumpfile("tb_d_latch.vcd");
		$dumpvars(0);
		t_in = 3'b000;
		repeat(8) begin
			#1 t_in <= t_in + 3'b001;
		end
	end
endmodule

modules_tb/tb_d_latch.vcd
$date
	Fri Jul 12 18:34:02 2019
$end
$version
	Icarus Verilog
$end
$timescale
	1s
$end
$scope module tb_d_latch $end
$var wire 1 ! out $end
$var reg 2 " t_in [1:0] $end
$scope module M1 $end
$var wire 1 # data $end
$var wire 1 $ enable $end
$var wire 1 ! out $end
$scope module sr_latch1 $end
$var wire 1 $ enable $end
$var wire 1 ! out $end
$var wire 1 % reset $end
$var wire 1 # set $end
$upscope $end
$upscope $end
$upscope $end
$enddefinitions $end
#0
$dumpvars
1%
0$
0#
b0 "
x!
$end
#1
0!
1$
b1 "
#2
0%
1#
0$
b10 "
#3
1!
1$
b11 "
#4
1%
0#
0$
b0 "
#5
0!
1$
b1 "
#6
0%
1#
0$
b10 "
#7
1!
1$
b11 "
#8
1%
0#
0$
b0 "
