modules/sr_latch.v
module sr_latch(input set, reset, enable, preset, clear, output reg out);
	always @* begin
		if (clear) out <= 1'b0;
		else if (preset) out <= 1'b1;
		else if (enable && reset) out <= 1'b0;
		else if (enable && set) out <= 1'b1;
	end
endmodule

modules/d_latch.v
`include "sr_latch.v"

module d_latch(input data, enable, preset, clear, output out);
	sr_latch sr_latch1(data, !data, enable, preset, clear, out);
endmodule

modules_tb/tb_d_latch.v
`include "d_latch.v"

module tb_d_latch;
	reg [3:0] t_in;
	wire out;

	d_latch M1(t_in[3], t_in[2], t_in[1], t_in[0], out);

	initial begin
		$dumpfile("tb_d_latch.vcd");
		$dumpvars(0);
		t_in = 4'b0000;
		repeat(16) begin
			#1 t_in <= t_in + 4'b0001;
		end
	end
endmodule

modules_tb/tb_d_latch.vcd
$date
	Sun Jul 28 05:18:38 2019
$end
$version
	Icarus Verilog
$end
$timescale
	1s
$end
$scope module tb_d_latch $end
$var wire 1 ! out $end
$var reg 4 " t_in [3:0] $end
$scope module M1 $end
$var wire 1 # clear $end
$var wire 1 $ data $end
$var wire 1 % enable $end
$var wire 1 & preset $end
$var wire 1 ! out $end
$scope module sr_latch1 $end
$var wire 1 # clear $end
$var wire 1 % enable $end
$var wire 1 & preset $end
$var wire 1 ' reset $end
$var wire 1 $ set $end
$var reg 1 ! out $end
$upscope $end
$upscope $end
$upscope $end
$enddefinitions $end
#0
$dumpvars
1'
0&
0%
0$
0#
b0 "
x!
$end
#1
0!
1#
b1 "
#2
1!
1&
0#
b10 "
#3
0!
1#
b11 "
#4
1%
0&
0#
b100 "
#5
1#
b101 "
#6
1!
1&
0#
b110 "
#7
0!
1#
b111 "
#8
0'
1$
0%
0&
0#
b1000 "
#9
1#
b1001 "
#10
1!
1&
0#
b1010 "
#11
0!
1#
b1011 "
#12
1!
1%
0&
0#
b1100 "
#13
0!
1#
b1101 "
#14
1!
1&
0#
b1110 "
#15
0!
1#
b1111 "
#16
1'
0$
0%
0&
0#
b0 "
