sr_latch.v
module sr_latch(input set, reset, enable, output out);
	assign out = (( out || ( set && enable)) && !( reset && enable));
endmodule

module test_sr_latch;
	reg [2:0] t_in;
	wire out;

	sr_latch M1(t_in[2], t_in[1], t_in[0], out);

	initial begin
		$dumpfile("test_sr_latch.vcd");
		$dumpvars(0,test_sr_latch);
		t_in = 3'b000;
		repeat(8) begin
			#1 t_in <= t_in + 3'b001;
		end
	end
endmodule

modules_tb/tb_sr_latch.v
`include "sr_latch.v"

module tb_sr_latch;
	reg [2:0] t_in;
	wire out;

	sr_latch M1(t_in[2], t_in[1], t_in[0], out);

	initial begin
		$dumpfile("tb_sr_latch.vcd");
		$dumpvars(0);
		t_in = 3'b000;
		repeat(8) begin
			#1 t_in <= t_in + 3'b001;
		end
	end
endmodule

modules_tb/tb_sr_latch.vcd
$date
	Thu Jul 25 15:27:18 2019
$end
$version
	Icarus Verilog
$end
$timescale
	1s
$end
$scope module tb_sr_latch $end
$var wire 1 ! out $end
$var reg 3 " t_in [2:0] $end
$scope module M1 $end
$var wire 1 # enable $end
$var wire 1 ! out $end
$var wire 1 $ reset $end
$var wire 1 % set $end
$upscope $end
$upscope $end
$enddefinitions $end
#0
$dumpvars
0%
0$
0#
b0 "
x!
$end
#1
1#
b1 "
#2
1$
0#
b10 "
#3
0!
1#
b11 "
#4
1%
0$
0#
b100 "
#5
1!
1#
b101 "
#6
1$
0#
b110 "
#7
0!
1#
b111 "
#8
1!
0%
0$
0#
b0 "
